django_celery_beat/__init__.py
django_celery_beat/admin.py
django_celery_beat/apps.py
django_celery_beat/clockedschedule.py
django_celery_beat/managers.py
django_celery_beat/models.py
django_celery_beat/multiple_time_schedule.py
django_celery_beat/schedulers.py
django_celery_beat/tzcrontab.py
django_celery_beat/utils.py
django_celery_beat/validators.py
django_celery_beat/migrations/0001_initial.py
django_celery_beat/migrations/0002_auto_20161118_0346.py
django_celery_beat/migrations/0003_auto_20161209_0049.py
django_celery_beat/migrations/0004_auto_20170221_0000.py
django_celery_beat/migrations/0005_add_solarschedule_events_choices.py
django_celery_beat/migrations/0006_auto_20180210_1226.py
django_celery_beat/migrations/0006_auto_20180322_0932.py
django_celery_beat/migrations/0006_periodictask_priority.py
django_celery_beat/migrations/0007_auto_20180521_0826.py
django_celery_beat/migrations/0008_auto_20180914_1922.py
django_celery_beat/migrations/0009_periodictask_headers.py
django_celery_beat/migrations/0010_auto_20190429_0326.py
django_celery_beat/migrations/0011_auto_20190508_0153.py
django_celery_beat/migrations/0012_periodictask_expire_seconds.py
django_celery_beat/migrations/0013_remove_clockedschedule_enabled.py
django_celery_beat/migrations/0014_auto_20200628_0259.py
django_celery_beat/migrations/__init__.py
django_celery_beat_yywing2-2.0.0.dist-info/AUTHORS
django_celery_beat_yywing2-2.0.0.dist-info/LICENSE
django_celery_beat_yywing2-2.0.0.dist-info/METADATA
django_celery_beat_yywing2-2.0.0.dist-info/WHEEL
django_celery_beat_yywing2-2.0.0.dist-info/entry_points.txt
django_celery_beat_yywing2-2.0.0.dist-info/top_level.txt
django_celery_beat_yywing2-2.0.0.dist-info/RECORD
