Metadata-Version: 2.1
Name: django-celery-beat-yywing2
Version: 2.0.0
Summary: Database-backed Periodic Tasks.
Home-page: https://github.com/celery/django-celery-beat
Author: Asif Saif Uddin, Ask Solem
Author-email: auvipy@gmail.com, ask@celeryproject.org
License: BSD
Keywords: django celery beat periodic task database
Platform: any
Classifier: Development Status :: 5 - Production/Stable
Classifier: License :: OSI Approved :: BSD License
Classifier: Programming Language :: Python
Classifier: Programming Language :: Python :: 3
Classifier: Programming Language :: Python :: 3.5
Classifier: Programming Language :: Python :: 3.6
Classifier: Programming Language :: Python :: 3.7
Classifier: Programming Language :: Python :: 3.8
Classifier: Programming Language :: Python :: Implementation :: CPython
Classifier: Programming Language :: Python :: Implementation :: PyPy
Classifier: Framework :: Django
Classifier: Framework :: Django :: 2.2
Classifier: Framework :: Django :: 3.0
Classifier: Operating System :: OS Independent
Classifier: Topic :: Communications
Classifier: Topic :: System :: Distributed Computing
Classifier: Topic :: Software Development :: Libraries :: Python Modules
Requires-Dist: django-timezone-field (<5.0,>=4.0)
Requires-Dist: python-crontab (>=2.3.4)
Requires-Dist: celery
Requires-Dist: Django (>=1.11.17)
